labs/lab3/src/verilog-rtl/dff32.v
module dff32( CLK, en, reset, Din, Qout);
input CLK, en, reset;
input [31:0] Din;
output reg [31:0] Qout;

always @(posedge CLK)
if(reset)
    Qout <= 32'h0;
else
begin
	if( en )
		Qout <= Din;
end

endmodule

labs/lab3/src/verilog/rtl/dff64.v
module dff64( CLK, en, reset, Din, Qout);
input CLK, en, reset;
input [63:0] Din;
output reg [63:0] Qout;

always @(posedge CLK)
if(reset)
    Qout <= 64'h0;
else
begin
	if( en )
		Qout <= Din;
end

endmodule

labs/lab3/src/verilog/rtl/psdsqrt.v
module psdsqrt(
        input clock,
				input reset,
				input start,
				input stop,
        input [5:0] NBITSIN,
				input [63:0] xin,
				output reg [31:0] sqrt
			  );

wire [31:0] aux;
wire [31:0] aux2;
wire [63:0] aux3;
wire [63:0] Q;
wire [63:0] sqtestsqrt;
wire [31:0] testsqrt;

reg [31:0] leftD;
reg [31:0] rightD;

reg [31:0] tempsqrt;
reg [31:0] rightQ;

always@(posedge clock)
begin
if(reset)
begin
	tempsqrt <= 32'h0;
	rightQ <= 32'h0;
end
else
begin
	tempsqrt <= leftD;
	rightQ <= rightD;
end
end

dff64 init(
		 .CLK(clock),
		 .en(start),
		 .reset(reset),
		 .Din(xin & aux3),
		 .Qout(Q)
		);

dff32 out(
		 .CLK(clock),
		 .en(stop),
		 .reset(reset),
		 .Din(tempsqrt),
		 .Qout(aux)
		);

assign sqtestsqrt = testsqrt * testsqrt;
assign testsqrt = tempsqrt | rightQ;
assign aux2 = 32'h1<<(NBITSIN/2-1);
assign aux3 = (32'h1<<NBITSIN) -1;

always @*
begin


if (start)
    leftD = 32'h0;
else
begin
    if (Q  >= (sqtestsqrt))
        leftD = testsqrt;
    else
        leftD = tempsqrt;
end

if (start)
begin
    rightD <= aux2;
end
else
    rightD = rightQ >> 1;

sqrt = aux;

end

endmodule

labs/lab3/src/verilog/testbench/psdsqrt_tb.v
/*
PSD 2021-2022

Lab 1 - Design and verification of a sequential square root calculator

	This Verilog code is property of University of Porto
	Its utilization beyond the scope of the course Digital Systems Design
	(Projeto de Sistemas Digitais) of the Master in Electrical
	and Computer Engineering requires explicit authorization from the author.

	jca@fe.up.pt, April 2022

*/

`timescale 1ns / 1ns



module psdsqrt_tb;

// general parameters
parameter CLOCK_PERIOD = 10;              // Clock period in ns
parameter MAX_SIM_TIME = 100_000_000;     // Set the maximum simulation time (time units=ns)


// Registers for driving the inputs:
reg  clock, reset;
reg  start, stop;
reg  [63:0] x;
reg [5:0] NBITSIN;
// Wires to connect to the outputs:
wire [31:0] sqrt;


// Instantiate the module under verification:
psdsqrt psdsqrt_1
      (
	    .clock(clock), // master clock, active in the positive edge
        .reset(reset), // master reset, synchronous and active high

        .start(start), // set to 1 during one clock cycle to start a sqrt
        .stop(stop),   // set to 1 during one clock cycle to load the output registers

				.NBITSIN(NBITSIN),
        .xin(x),       // the operands
        .sqrt(sqrt)
        );


//---------------------------------------------------
// Setup initial signals
integer data_file    ; // file handler
integer scan_file    ; // file handler
logic [5:0] arg0; //bytes
logic [63:0] arg1; //sqrt test
`define NULL 0    


initial
begin
	data_file = $fopen("simargs.txt", "r");
	if (data_file == `NULL) begin
		$display("data_file handle was NULL");
		$finish;
	end

	scan_file = $fscanf(data_file, "%d\n", arg0);
	scan_file = $fscanf(data_file, "%d\n", arg1);
	$display("Numero de bits: %d", arg0);
	$display("Raiz de: %d", arg1);

	NBITSIN = arg0;
	clock = 1'b0;
	reset = 1'b0;
	x = 0;
	start = 1'b0;
	stop  = 1'b0;
end

//---------------------------------------------------
// generate a 50% duty-cycle clock signal
initial
begin
  forever
    # (CLOCK_PERIOD / 2 ) clock = ~clock;
end

//---------------------------------------------------
// Apply the initial reset for 2 clock cycles:
initial
begin
  # (CLOCK_PERIOD/3) // wait a fraction of the clock period to
                     // misalign the reset pulse with the clock edges:
  reset = 1;
  # (2 * CLOCK_PERIOD ) // apply the reset for 2 clock periods
  reset = 0;
end

//---------------------------------------------------
// Set the maximum simulation time:
initial
begin
  # ( MAX_SIM_TIME )
  $stop;
end

initial
begin
	$dumpfile("mysimdata.vcd");// The filename with the waveform data
	$dumpvars(0, psdsqrt_tb);
// The root node to dump
end

//---------------------------------------------------
// The verification program (THIS IS TRUE A PROGRAM!)

initial
begin

  // Wait 10 clock periods
  #( 10*CLOCK_PERIOD );

  // Example of calling task 'execsqrt':
  execsqrt( arg1 );

  // Example of calling the golden sqrt function:
  $display("%d",  golden_sqrt( arg1 ) );

  $display("Groupid = %h", `GROUPID );

  // COMPLETE..

  #( 10*CLOCK_PERIOD );
  $stop;
end


//---------------------------------------------------
// Simulate the sequential controller to perform a square root.
task execsqrt;
input [31:0] xin;
begin
  x = xin;   // Apply operands
  @(negedge clock);
  start = 1'b1;       // Assert start
  @(negedge clock );
  start = 1'b0;
  repeat (16) @(posedge clock);  // Execute division
  @(negedge clock);
  stop = 1'b1;        // Assert stop
  @(negedge clock);
  stop = 1'b0;
  @(negedge clock);

  // Print the results:
  // You may not watt to do this when verifying some millions of operands...
  // Add a flag to enable/disable this print

  $display("SQRT(%d) = %d", x, sqrt );
  end
endtask



//---------------------------------------------------
// A Verilog function implementing the same SQRT algorithm
// This is the "golden" function whose result should be exact
// bit by bit with the result created by your circuit.
// Note this does not include the rounding process nor
// supports the parameterization for different number of bits
function [15:0] golden_sqrt( input [31:0] xin );
reg   [15:0] mask;
reg   [15:0] temproot;
integer i;
begin
  mask = 16'b1000_0000_0000_0000;
  temproot = 0;
  for (i=0; i<16; i=i+1 )
  begin
    if (  xin >= ( temproot | mask ) * (temproot | mask ) )
      temproot = temproot | mask;
    mask = mask >> 1;
  end
  golden_sqrt = temproot;
end
endfunction

endmodule

labs/lab3/sim/mysimdata.vcd
$date
	Fri Apr 29 21:32:59 2022
$end
$version
	Icarus Verilog
$end
$timescale
	1ns
$end
$scope module psdsqrt_tb $end
$var wire 32 ! sqrt [31:0] $end
$var reg 6 " NBITSIN [5:0] $end
$var reg 6 # arg0 [5:0] $end
$var reg 64 $ arg1 [63:0] $end
$var reg 1 % clock $end
$var reg 1 & reset $end
$var reg 1 ' start $end
$var reg 1 ( stop $end
$var reg 64 ) x [63:0] $end
$var integer 32 * data_file [31:0] $end
$var integer 32 + scan_file [31:0] $end
$scope function golden_sqrt $end
$var reg 16 , mask [15:0] $end
$var reg 16 - temproot [15:0] $end
$var reg 32 . xin [31:0] $end
$var integer 32 / i [31:0] $end
$upscope $end
$scope module psdsqrt_1 $end
$var wire 6 0 NBITSIN [5:0] $end
$var wire 1 % clock $end
$var wire 1 & reset $end
$var wire 1 ' start $end
$var wire 1 ( stop $end
$var wire 32 1 testsqrt [31:0] $end
$var wire 64 2 xin [63:0] $end
$var wire 64 3 sqtestsqrt [63:0] $end
$var wire 64 4 aux3 [63:0] $end
$var wire 32 5 aux2 [31:0] $end
$var wire 32 6 aux [31:0] $end
$var wire 64 7 Q [63:0] $end
$var reg 32 8 leftD [31:0] $end
$var reg 32 9 rightD [31:0] $end
$var reg 32 : rightQ [31:0] $end
$var reg 32 ; sqrt [31:0] $end
$var reg 32 < tempsqrt [31:0] $end
$scope module init $end
$var wire 1 % CLK $end
$var wire 64 = Din [63:0] $end
$var wire 1 ' en $end
$var wire 1 & reset $end
$var reg 64 > Qout [63:0] $end
$upscope $end
$scope module out $end
$var wire 1 % CLK $end
$var wire 32 ? Din [31:0] $end
$var wire 1 ( en $end
$var wire 1 & reset $end
$var reg 32 @ Qout [31:0] $end
$upscope $end
$upscope $end
$scope task execsqrt $end
$var reg 32 A xin [31:0] $end
$upscope $end
$upscope $end
$enddefinitions $end
#0
$dumpvars
bx A
bx @
bx ?
bx >
b0 =
bx <
bx ;
bx :
b0xxxxxxxxxxxxxxxxxxxxxxxxxxxxxxx 9
bx 8
bx 7
bx 6
b1000000000000000 5
b11111111111111111111111111111111 4
bx 3
b0 2
bx 1
b100000 0
bx /
bx .
bx -
bx ,
b1 +
b10000000000000000000000000000011 *
b0 )
0(
0'
0&
0%
b1010001 $
b100000 #
b100000 "
bx !
$end
#3
1&
#5
b0 !
b0 ;
b0 9
b0 8
b0 3
b0 1
b0 7
b0 >
b0 6
b0 @
b0 :
b0 <
b0 ?
1%
#10
0%
#15
1%
#20
0%
#23
0&
#25
1%
#30
0%
#35
1%
#40
0%
#45
1%
#50
0%
#55
1%
#60
0%
#65
1%
#70
0%
#75
1%
#80
0%
#85
1%
#90
0%
#95
1%
#100
b1000000000000000 9
1'
b1010001 =
0%
b1010001 )
b1010001 2
b1010001 A
#105
b1000000000000000000000000000000 3
b1000000000000000 1
b1010001 7
b1010001 >
b1000000000000000 :
1%
#110
b100000000000000 9
0'
0%
#115
b10000000000000 9
b10000000000000000000000000000 3
b100000000000000 1
b100000000000000 :
1%
#120
0%
#125
b1000000000000 9
b100000000000000000000000000 3
b10000000000000 1
b10000000000000 :
1%
#130
0%
#135
b100000000000 9
b1000000000000000000000000 3
b1000000000000 1
b1000000000000 :
1%
#140
0%
#145
b10000000000 9
b10000000000000000000000 3
b100000000000 1
b100000000000 :
1%
#150
0%
#155
b1000000000 9
b100000000000000000000 3
b10000000000 1
b10000000000 :
1%
#160
0%
#165
b100000000 9
b1000000000000000000 3
b1000000000 1
b1000000000 :
1%
#170
0%
#175
b10000000 9
b10000000000000000 3
b100000000 1
b100000000 :
1%
#180
0%
#185
b1000000 9
b100000000000000 3
b10000000 1
b10000000 :
1%
#190
0%
#195
b100000 9
b1000000000000 3
b1000000 1
b1000000 :
1%
#200
0%
#205
b10000 9
b10000000000 3
b100000 1
b100000 :
1%
#210
0%
#215
b1000 9
b100000000 3
b10000 1
b10000 :
1%
#220
0%
#225
b100 9
b1000 8
b1000000 3
b1000 1
b1000 :
1%
#230
0%
#235
b10 9
b10010000 3
b1100 1
b100 :
b1000 <
b1000 ?
1%
#240
0%
#245
b1 9
b1100100 3
b1010 1
b10 :
1%
#250
0%
#255
b0 9
b1001 8
b1010001 3
b1001 1
b1 :
1%
#260
0%
#265
b0 :
b1001 <
b1001 ?
1%
#270
1(
0%
#275
b1001 !
b1001 ;
b1001 6
b1001 @
1%
#280
0(
0%
#285
1%
#290
b10000 /
b1001 -
b0 ,
b1010001 .
0%
